us_kafka/__init__.py
us_kafka/consumer/__init__.py
us_kafka/consumer/base_consumer.py
us_kafka/producer/__init__.py
us_kafka/producer/base_producer.py
us_kafka-0.0.1.dist-info/METADATA
us_kafka-0.0.1.dist-info/WHEEL
us_kafka-0.0.1.dist-info/top_level.txt
us_kafka-0.0.1.dist-info/RECORD
